{
  "sportmonks_fixture_id": 1059944,
  "fetched_at": "2026-06-23T07:01:31.003105+00:00",
  "status_code": 200,
  "payload": {
    "data": {
      "id": 1059944,
      "sport_id": 1,
      "league_id": 5,
      "season_id": 5326,
      "stage_id": 9960,
      "group_id": null,
      "aggregate_id": 25144,
      "round_id": null,
      "state_id": 5,
      "venue_id": null,
      "name": "Osasuna vs Rennes",
      "starting_at": "2005-09-28 22:00:00",
      "result_info": "Game ended in draw.",
      "leg": "2/2",
      "details": null,
      "length": 90,
      "placeholder": false,
      "has_odds": false,
      "has_premium_odds": false,
      "starting_at_timestamp": 1127944800,
      "participants": [
        {
          "id": 459,
          "sport_id": 1,
          "country_id": 32,
          "venue_id": 56,
          "gender": "male",
          "name": "Osasuna",
          "short_code": "OSA",
          "image_path": "https://cdn.sportmonks.com/images/soccer/teams/11/459.png",
          "founded": 1920,
          "type": "domestic",
          "placeholder": false,
          "last_played_at": "2026-05-23 19:00:00",
          "meta": {
            "location": "home",
            "winner": false,
            "position": null
          }
        },
        {
          "id": 598,
          "sport_id": 1,
          "country_id": 17,
          "venue_id": 135,
          "gender": "male",
          "name": "Rennes",
          "short_code": "REN",
          "image_path": "https://cdn.sportmonks.com/images/soccer/teams/22/598.png",
          "founded": 1901,
          "type": "domestic",
          "placeholder": false,
          "last_played_at": "2026-06-20 15:30:00",
          "meta": {
            "location": "away",
            "winner": false,
            "position": null
          }
        }
      ],
      "scores": [
        {
          "id": 5661978,
          "fixture_id": 1059944,
          "type_id": 1,
          "participant_id": 459,
          "score": {
            "goals": 0,
            "participant": "home"
          },
          "description": "1ST_HALF"
        },
        {
          "id": 5661983,
          "fixture_id": 1059944,
          "type_id": 1525,
          "participant_id": 598,
          "score": {
            "goals": 0,
            "participant": "away"
          },
          "description": "CURRENT"
        },
        {
          "id": 5661980,
          "fixture_id": 1059944,
          "type_id": 2,
          "participant_id": 459,
          "score": {
            "goals": 0,
            "participant": "home"
          },
          "description": "2ND_HALF"
        },
        {
          "id": 5661979,
          "fixture_id": 1059944,
          "type_id": 1,
          "participant_id": 598,
          "score": {
            "goals": 0,
            "participant": "away"
          },
          "description": "1ST_HALF"
        },
        {
          "id": 5661981,
          "fixture_id": 1059944,
          "type_id": 2,
          "participant_id": 598,
          "score": {
            "goals": 0,
            "participant": "away"
          },
          "description": "2ND_HALF"
        },
        {
          "id": 5661982,
          "fixture_id": 1059944,
          "type_id": 1525,
          "participant_id": 459,
          "score": {
            "goals": 0,
            "participant": "home"
          },
          "description": "CURRENT"
        }
      ],
      "state": {
        "id": 5,
        "state": "FT",
        "name": "Full Time",
        "short_name": "FT",
        "developer_name": "FT"
      },
      "events": [],
      "statistics": [],
      "lineups": [],
      "formations": [],
      "xgfixture": [],
      "pressure": [],
      "odds": [],
      "predictions": [],
      "form": []
    },
    "subscription": [
      {
        "meta": {
          "current_timestamp": 1782198091,
          "next_billing_cycle": "2026-07-22T10:41:23 UTC"
        },
        "plans": [
          {
            "plan": "Euro Club Tournaments",
            "sport": "Football",
            "category": "All-in"
          }
        ],
        "add_ons": [],
        "widgets": [],
        "bundles": []
      }
    ],
    "rate_limit": {
      "resets_in_seconds": 3589,
      "remaining": 2478,
      "requested_entity": "Fixture"
    },
    "timezone": "UTC"
  }
}